amq/__init__.py
amq/amq.py
iamq-0.0.1.dist-info/LICENSE
iamq-0.0.1.dist-info/METADATA
iamq-0.0.1.dist-info/WHEEL
iamq-0.0.1.dist-info/top_level.txt
iamq-0.0.1.dist-info/RECORD
